nodemon/__main__.py
nodemon/amend_dialog.py
nodemon/animated_structures.py
nodemon/canvas_frame.py
nodemon/draw_controls_frame.py
nodemon/node_demonstrator.py
nodemon/optimisation_frames.py
nodemon/rename_dialog.py
nodemon/representation_frame.py
nodemon/state_model.py
nodemon/structures.py
nodemon/tool_frame.py
nodemon/trace_frame.py
nodemon/traversal_frames.py
nodemon/usage_controls_frame.py
nodemon-0.1.1.dist-info/METADATA
nodemon-0.1.1.dist-info/WHEEL
nodemon-0.1.1.dist-info/licenses/LICENSE
nodemon-0.1.1.dist-info/RECORD
