Metadata-Version: 2.4
Name: nodemon
Version: 0.1.1
Summary: A simple drag and drop application to help visualise various graph algorithms
Project-URL: Homepage, https://github.com/MrHarcombe/NodeDemonstrator
Project-URL: Issues, https://github.com/MrHarcombe/NodeDemonstrator/issues
Author-email: Ian Harcombe <ian.harcombe@gmail.com>
License:                     GNU GENERAL PUBLIC LICENSE
License-File: LICENSE
Classifier: Development Status :: 4 - Beta
Classifier: Intended Audience :: Education
Classifier: License :: OSI Approved :: GNU General Public License v3 (GPLv3)
Classifier: Operating System :: OS Independent
Classifier: Programming Language :: Python :: 3
Classifier: Topic :: Education
Requires-Python: >=3.10
Requires-Dist: ttkbootstrap>=1.14.0
